neuralseek/__init__.py
neuralseek/_hooks/__init__.py
neuralseek/_hooks/registration.py
neuralseek/_hooks/sdkhooks.py
neuralseek/_hooks/types.py
neuralseek/_version.py
neuralseek/analytics.py
neuralseek/answerratings.py
neuralseek/basesdk.py
neuralseek/categorize.py
neuralseek/extractentities.py
neuralseek/findpii.py
neuralseek/httpclient.py
neuralseek/identifylanguage.py
neuralseek/identifylanguagejson.py
neuralseek/keycheck.py
neuralseek/logs.py
neuralseek/maistro.py
neuralseek/models/__init__.py
neuralseek/models/analyticsop.py
neuralseek/models/answerratingsop.py
neuralseek/models/apierror.py
neuralseek/models/categorizeop.py
neuralseek/models/deleteuserdataop.py
neuralseek/models/extractentitiesop.py
neuralseek/models/identifylanguagejsonop.py
neuralseek/models/identifylanguageop.py
neuralseek/models/logsop.py
neuralseek/models/maistroop.py
neuralseek/models/otpop.py
neuralseek/models/piiop.py
neuralseek/models/rateop.py
neuralseek/models/scoreop.py
neuralseek/models/security.py
neuralseek/models/seek.py
neuralseek/models/seek_response.py
neuralseek/models/test_jsonop.py
neuralseek/models/test_multipartop.py
neuralseek/models/trainop.py
neuralseek/models/translateglossary_jsonop.py
neuralseek/models/translateglossary_multipartop.py
neuralseek/models/translateop.py
neuralseek/onetimepassword.py
neuralseek/py.typed
neuralseek/rate.py
neuralseek/score.py
neuralseek/sdk.py
neuralseek/sdkconfiguration.py
neuralseek/seek_sdk.py
neuralseek/servicetest.py
neuralseek/testquestions.py
neuralseek/testresults.py
neuralseek/train.py
neuralseek/translate.py
neuralseek/translationglossary.py
neuralseek/types/__init__.py
neuralseek/types/basemodel.py
neuralseek/userdata.py
neuralseek/utils/__init__.py
neuralseek/utils/annotations.py
neuralseek/utils/enums.py
neuralseek/utils/eventstreaming.py
neuralseek/utils/forms.py
neuralseek/utils/headers.py
neuralseek/utils/logger.py
neuralseek/utils/metadata.py
neuralseek/utils/queryparams.py
neuralseek/utils/requestbodies.py
neuralseek-1.1.0.dist-info/METADATA
neuralseek-1.1.0.dist-info/WHEEL
neuralseek-1.1.0.dist-info/RECORD
